OneLib/__init__.py
OneLib/Time/ETA.py
OneLib/Time/Timer.py
OneLib/Time/__init__.py
OneLib/Time/test_eta.py
OneLib/pytest_depends/__init__.py
OneLib/pytest_depends/plugin.py
OneLib/tp_checker/__init__.py
OneLib/tp_checker/tp_checker.py
OneLib-0.3.4.dist-info/DESCRIPTION.rst
OneLib-0.3.4.dist-info/METADATA
OneLib-0.3.4.dist-info/RECORD
OneLib-0.3.4.dist-info/WHEEL
OneLib-0.3.4.dist-info/metadata.json
OneLib-0.3.4.dist-info/top_level.txt
