Metadata-Version: 2.0
Name: OneLib
Version: 0.3.4
Summary: my little tool set
Home-page: https://github.com/gaoyuanhezhihao/pyLib
Author: He Zhihao
Author-email: gaoyuanhezhihao@gmail.com
License: MIT
Keywords: testing,logging,example
Platform: UNKNOWN
Classifier: Development Status :: 3 - Alpha
Classifier: Intended Audience :: Developers
Classifier: Topic :: Software Development :: Build Tools
Classifier: License :: OSI Approved :: MIT License
Classifier: Programming Language :: Python :: 3.4
Classifier: Programming Language :: Python :: 3.5
